LICENSE
README.md
requirements.txt
setup.py
finder_tags_butler/__init__.py
finder_tags_butler/__main__.py
finder_tags_butler/cli_layer.py
finder_tags_butler/controller_layer.py
finder_tags_butler/errors.py
finder_tags_butler/logic_layer.py
finder_tags_butler/logic_tags.py
finder_tags_butler/properties.py
finder_tags_butler.egg-info/PKG-INFO
finder_tags_butler.egg-info/SOURCES.txt
finder_tags_butler.egg-info/dependency_links.txt
finder_tags_butler.egg-info/entry_points.txt
finder_tags_butler.egg-info/requires.txt
finder_tags_butler.egg-info/top_level.txt
test/test_integration_logic_layer.py
test/test_unit_logic_tags.py