Metadata-Version: 2.1
Name: finder-tags-butler
Version: 0.1.dev1
Summary: Synchronize Mac OS Finder tags between several machines
Home-page: https://github.com/bglezseoane/finder-tags-butler
Author: Borja González Seoane
Author-email: garaje@glezseoane.es
License: LICENSE
Download-URL: https://github.com/bglezseoane/finder-tags-butler/archive/0.1.dev1.tar.gz
Platform: UNKNOWN
Classifier: License :: OSI Approved :: GNU General Public License v3 (GPLv3)
Classifier: Intended Audience :: End Users/Desktop
Classifier: Intended Audience :: Developers
Classifier: Development Status :: 1 - Planning
Classifier: Programming Language :: Python
Classifier: Programming Language :: Python :: 3
Classifier: Operating System :: MacOS
Classifier: Topic :: Utilities
Classifier: Topic :: System :: Filesystems
Requires-Python: >=3.8.5
